kroman
