Metadata-Version: 1.0
Name: kroman
Version: 1.1
Summary: Kroman is Korean romanization tool.
Home-page: https://github.com/cheunghy/kroman-py
Author: Zhang Kai Yu
Author-email: yeannylam@gmail.com
License: MIT
Platform: UNKNOWN
